pyepsilla/__init__.py
pyepsilla/cloud/__init__.py
pyepsilla/cloud/client.py
pyepsilla/cloud/readme.md
pyepsilla/cloud/sentry.py
pyepsilla/enterprise/__init__.py
pyepsilla/enterprise/client.py
pyepsilla/enterprise/readme.md
pyepsilla/enterprise/sentry.py
pyepsilla/utils/__init__.py
pyepsilla/utils/rag.py
pyepsilla/utils/search_engine.py
pyepsilla/vectordb/__init__.py
pyepsilla/vectordb/client.py
pyepsilla/vectordb/field.py
pyepsilla/vectordb/machineid/__init__.py
pyepsilla/vectordb/machineid/py.typed
pyepsilla/vectordb/readme.md
pyepsilla/vectordb/sentry.py
pyepsilla/vectordb/telemetry.py
pyepsilla/vectordb/utils/__init__.py
pyepsilla/vectordb/utils/embedding_functions.py
pyepsilla/vectordb/version.py
pyepsilla-0.3.15.dist-info/METADATA
pyepsilla-0.3.15.dist-info/WHEEL
pyepsilla-0.3.15.dist-info/licenses/LICENSE.txt
pyepsilla-0.3.15.dist-info/RECORD
