Metadata-Version: 2.4
Name: pyepsilla
Version: 0.3.15
Summary: 
License-File: LICENSE.txt
Author: Epsilla
Author-email: info@epsilla.com
Requires-Python: >=3.8
Classifier: Programming Language :: Python :: 3
Classifier: Programming Language :: Python :: 3.8
Classifier: Programming Language :: Python :: 3.9
Classifier: Programming Language :: Python :: 3.10
Classifier: Programming Language :: Python :: 3.11
Classifier: Programming Language :: Python :: 3.12
Classifier: Programming Language :: Python :: 3.13
Classifier: Programming Language :: Python :: 3.14
Requires-Dist: posthog (>=3.2.0)
Requires-Dist: py-machineid (>=0.5.0)
Requires-Dist: pydantic (>=2.6.0)
Requires-Dist: requests (>=2.32.2)
Requires-Dist: sentry-sdk (>=2.2.0)
